latex_gen_small/__init__.py
latex_gen_small/latex_gen_small.py
latex_gen_small-0.1.4.dist-info/METADATA
latex_gen_small-0.1.4.dist-info/WHEEL
latex_gen_small-0.1.4.dist-info/RECORD
