Metadata-Version: 2.1
Name: latex-gen-small
Version: 0.1.4
Summary: 
Author: Anton Shiryaev
Author-email: med.phisiker@gmail.com
Requires-Python: >=3.10,<4.0
Classifier: Programming Language :: Python :: 3
Classifier: Programming Language :: Python :: 3.10
Classifier: Programming Language :: Python :: 3.11
Classifier: Programming Language :: Python :: 3.12
